{
  "file": "script88.py",
  "logs": [
    {
      "candidate_id": 33,
      "lineno": 138,
      "col_offset": 0,
      "kind": "func_entry",
      "log_code": "logging.DEBUG(\"Entering push_alerts with %d alerts\", len(alerts))"
    },
    {
      "candidate_id": 36,
      "lineno": 147,
      "col_offset": 0,
      "kind": "except",
      "log_code": "logging.ERROR(\"Failed to push alerts to remote endpoint\")"
    },
    {
      "candidate_id": 38,
      "lineno": 151,
      "col_offset": 0,
      "kind": "func_entry",
      "log_code": "logging.DEBUG(\"Loading MonitoringState from %s\", path)"
    },
    {
      "candidate_id": 41,
      "lineno": 158,
      "col_offset": 0,
      "kind": "except",
      "log_code": "logging.ERROR(\"Error while loading MonitoringState, using fallback\")"
    },
    {
      "candidate_id": 43,
      "lineno": 162,
      "col_offset": 0,
      "kind": "func_entry",
      "log_code": "logging.DEBUG(\"Saving MonitoringState to %s\", path)"
    },
    {
      "candidate_id": 44,
      "lineno": 168,
      "col_offset": 0,
      "kind": "except",
      "log_code": "logging.ERROR(\"Failed to persist MonitoringState to disk\")"
    },
    {
      "candidate_id": 46,
      "lineno": 172,
      "col_offset": 0,
      "kind": "func_entry",
      "log_code": "logging.DEBUG(\"Computing statistics for %d readings\", len(state.readings))"
    },
    {
      "candidate_id": 48,
      "lineno": 184,
      "col_offset": 0,
      "kind": "before_return",
      "log_code": "logging.INFO(\"Computed stats: count=%d avg=%s\", len(state.readings), avg)"
    },
    {
      "candidate_id": 56,
      "lineno": 241,
      "col_offset": 0,
      "kind": "func_entry",
      "log_code": "logging.DEBUG(\"Starting main with data_dir=%s base_url=%s\", data_dir, base_url)"
    },
    {
      "candidate_id": 57,
      "lineno": 272,
      "col_offset": 0,
      "kind": "except",
      "log_code": "logging.ERROR(\"Unhandled error in main, exiting with code 1\")"
    },
    {
      "candidate_id": 59,
      "lineno": 273,
      "col_offset": 0,
      "kind": "before_return",
      "log_code": "logging.INFO(\"Main completed successfully, exiting with code 0\")"
    }
  ]
}
